{
  "name": "Ecommerce Proto",
  "dockerComposeFile": ["../docker-compose.dev.yml"],
  "service": "proto",
  "workspaceFolder": "/workspace",
  "shutdownAction": "stopCompose",

  "customizations": {
    "vscode": {
      "extensions": [
        "bufbuild.vscode-buf",
        "zxh404.vscode-proto3"
      ],
      "settings": {
        "editor.formatOnSave": true,
        "[proto3]": {
          "editor.defaultFormatter": "bufbuild.vscode-buf"
        }
      }
    }
  },

  "postCreateCommand": "buf --version && echo '✅ Prêt. Commandes : buf lint, buf breaking'"
}